mcmetadata/__init__.py
mcmetadata/content.py
mcmetadata/dates.py
mcmetadata/exceptions.py
mcmetadata/feeds.py
mcmetadata/languages.py
mcmetadata/py.typed
mcmetadata/requests_arcana.py
mcmetadata/text.py
mcmetadata/titles.py
mcmetadata/urls.py
mcmetadata/urlshortners.py
mcmetadata/webpages.py
mcmetadata/data/domain-skip-list.txt
mcmetadata/test/__init__.py
mcmetadata/test/test_content.py
mcmetadata/test/test_dates.py
mcmetadata/test/test_extract.py
mcmetadata/test/test_feeds.py
mcmetadata/test/test_languages.py
mcmetadata/test/test_titles.py
mcmetadata/test/test_urls.py
mcmetadata/test/test_webpages.py
mcmetadata/test/fixtures/bloomberg-no-meta.html
mcmetadata/test/fixtures/bloomberg-original.html
mcmetadata/test/fixtures/cached-httparchiveorg
mcmetadata/test/fixtures/cached-httpgpogovfdsyspkgpl
mcmetadata/test/fixtures/cached-httpmysitecom
mcmetadata/test/fixtures/cached-httpnewsmachetecompage2
mcmetadata/test/fixtures/cached-httpnytims4K9g6u
mcmetadata/test/fixtures/cached-httppeoplesdailyngcomfeed
mcmetadata/test/fixtures/cached-httpsapifollowittrackrssstoryclickv3ecuhSAhRa8kTTPWTA7xaXioxzwoq1nFt
mcmetadata/test/fixtures/cached-httpscnnit3wGkGU1
mcmetadata/test/fixtures/cached-httpsdatatherapywordpresscom20190313aligningyourdataandmethodsyourmission
mcmetadata/test/fixtures/cached-httpsg1globocompipiauinoticia20230102mulhereesfaqueadapeloexnamoradodentrodecasanosuldopiauightml
mcmetadata/test/fixtures/cached-httpsobservadorvsportsptembd75404m9812obsrv53a58b677b53143428e47d43d5887139autostartfalse
mcmetadata/test/fixtures/cached-httpsobserversfrance24comen20190826mexicoafricanmigrantstrappedprotestjourney
mcmetadata/test/fixtures/cached-httpsradioaliancacombrplantaohomemde24anosemortoporgolpesdefacaemconcordiananoitedequartafeira
mcmetadata/test/fixtures/cached-httpsthekenyatimescomcountieskisumutradersalertedaboutcartelsinstallsissuance
mcmetadata/test/fixtures/cached-httpstravelgcca
mcmetadata/test/fixtures/cached-httpsupstractcomxfdf95bf448e1f2a8
mediacloud_metadata-1.4.1.dist-info/WHEEL
mediacloud_metadata-1.4.1.dist-info/METADATA
mediacloud_metadata-1.4.1.dist-info/RECORD
