Metadata-Version: 2.3
Name: mediacloud-metadata
Version: 1.4.1
Summary: Media Cloud news article metadata extraction
Author-email: Rahul Bhargava <rahul@mediacloud.org>
Requires-Python: >=3.10
Classifier: License :: OSI Approved :: Apache Software License
Classifier: Natural Language :: English
Classifier: Operating System :: OS Independent
Classifier: Programming Language :: Python
Classifier: Programming Language :: Python :: 3.10
Classifier: Programming Language :: Python :: 3.11
Requires-Dist: htmldate==1.8.*
Requires-Dist: dateparser==1.2.*
Requires-Dist: tldextract==5.1.*
Requires-Dist: url-normalize==1.4.*
Requires-Dist: furl==2.1.*
Requires-Dist: py3langid==0.2.*
Requires-Dist: newspaper3k==0.2.*
Requires-Dist: goose3==3.1.*
Requires-Dist: BeautifulSoup4==4.12.*
Requires-Dist: readability-lxml==0.8.*
Requires-Dist: trafilatura==1.8.*
Requires-Dist: boilerpy3==1.0.*
Requires-Dist: requests
Requires-Dist: faust-cchardet==2.1.*
Requires-Dist: surt==0.3.1
Requires-Dist: pre-commit==3.8.* ; extra == "dev"
Requires-Dist: flake8==6.1.* ; extra == "dev"
Requires-Dist: mypy==1.6.* ; extra == "dev"
Requires-Dist: isort==5.12.* ; extra == "dev"
Requires-Dist: types-urllib3==1.26.* ; extra == "dev"
Requires-Dist: types-requests==2.32.* ; extra == "dev"
Requires-Dist: black==24.4.* ; extra == "dev"
Requires-Dist: pytest ; extra == "test"
Requires-Dist: parameterized ; extra == "test"
Project-URL: Bug Tracker, https://github.com/mediacloud/meta-extractor/issues
Project-URL: Homepage, https://mediacloud.org
Project-URL: Source Code, https://github.com/mediacloud/meta-extractor
Provides-Extra: dev
Provides-Extra: test
